{
	"compilerOptions": {
		"target": "esnext",
		"module": "esnext",
		"moduleResolution": "bundler",
		"moduleDetection": "force",
		"ignoreDeprecations": "6.0",
		"allowImportingTsExtensions": true,
		"allowSyntheticDefaultImports": true,
		"esModuleInterop": true,
		"isolatedModules": true,
		"allowJs": true,
		"skipLibCheck": true,
		"useDefineForClassFields": true,
		"strict": true,
		"noUnusedLocals": true,
		"noUnusedParameters": true,
		"erasableSyntaxOnly": false,
		"noFallthroughCasesInSwitch": true,
		"noUncheckedSideEffectImports": true
	},
	"exclude": [
		"node_modules",
		"dist"
	]
}
